{
 "type": "USJ",
 "version": "3.1",
 "content": [
  {
   "type": "book",
   "marker": "id",
   "code": "3JN",
   "content": [
    "- Open English Translation—Readers’ Version (OET-RV) v0.1.02"
   ]
  },
  {
   "type": "para",
   "marker": "ide",
   "content": [
    "UTF-8\n"
   ]
  },
  {
   "type": "para",
   "marker": "rem",
   "content": [
    "ESFM v0.6 JN3\n"
   ]
  },
  {
   "type": "para",
   "marker": "rem",
   "content": [
    "WORDTABLE OET-LV_NT_word_table.tsv\n"
   ]
  },
  {
   "type": "para",
   "marker": "h",
   "content": [
    "3 Yohan\n"
   ]
  },
  {
   "type": "para",
   "marker": "toc1",
   "content": [
    "3 Yohan (John)\n"
   ]
  },
  {
   "type": "para",
   "marker": "toc2",
   "content": [
    "3 Yohan\n"
   ]
  },
  {
   "type": "para",
   "marker": "toc3",
   "content": [
    "3 Yn\n"
   ]
  },
  {
   "type": "para",
   "marker": "mt2",
   "content": [
    "The third letter\n"
   ]
  },
  {
   "type": "para",
   "marker": "mt2",
   "content": [
    "that we have written by\n"
   ]
  },
  {
   "type": "para",
   "marker": "mt1",
   "content": [
    "Yohan (John)\n"
   ]
  },
  {
   "type": "para",
   "marker": "is1",
   "content": [
    "Introduction\n"
   ]
  },
  {
   "type": "para",
   "marker": "is2",
   "content": [
    "The author\n"
   ]
  },
  {
   "type": "para",
   "marker": "ip",
   "content": [
    "This the third letter we have that was written by Yohan, one of the twelve apprentices who spent the most time with Yeshua.\n"
   ]
  },
  {
   "type": "para",
   "marker": "is2",
   "content": [
    "This letter\n"
   ]
  },
  {
   "type": "para",
   "marker": "ip",
   "content": [
    "This letter was sent to one of Yohan’s friends named Gaius. Yohan praises Gaius for the way he’d looked after other believers and for his living out God’s truth. Yohan also warns Gaius about a person named Diotrephes who was opposing the believers.\n"
   ]
  },
  {
   "type": "para",
   "marker": "iot",
   "content": [
    "Main components of Yohan’s letter\n"
   ]
  },
  {
   "type": "para",
   "marker": "io1",
   "content": [
    "Greetings ",
    {
     "type": "char",
     "marker": "ior",
     "content": [
      "1-4"
     ]
    }
   ]
  },
  {
   "type": "para",
   "marker": "io1",
   "content": [
    "Praising Gaius ",
    {
     "type": "char",
     "marker": "ior",
     "content": [
      "5-8"
     ]
    }
   ]
  },
  {
   "type": "para",
   "marker": "io1",
   "content": [
    "Scolding Diotrephes ",
    {
     "type": "char",
     "marker": "ior",
     "content": [
      "9-10"
     ]
    }
   ]
  },
  {
   "type": "para",
   "marker": "io1",
   "content": [
    "Boasting about Demetrius ",
    {
     "type": "char",
     "marker": "ior",
     "content": [
      "11-12"
     ]
    }
   ]
  },
  {
   "type": "para",
   "marker": "io1",
   "content": [
    "The closing ",
    {
     "type": "char",
     "marker": "ior",
     "content": [
      "13-15"
     ]
    }
   ]
  },
  {
   "type": "para",
   "marker": "rem",
   "content": [
    "This is still a very early look into the unfinished text of the Open English Translation of the Bible. Please double-check the text in advance before using in public.\n"
   ]
  },
  {
   "type": "para",
   "marker": "ie",
   "content": []
  },
  {
   "type": "chapter",
   "marker": "c",
   "number": "1",
   "sid": "3JN 1"
  },
  {
   "type": "para",
   "marker": "rem",
   "content": [
    "/s1 Salutation\n"
   ]
  },
  {
   "type": "para",
   "marker": "rem",
   "content": [
    "/s1 Greetings\n"
   ]
  },
  {
   "type": "para",
   "marker": "rem",
   "content": [
    "/s1 Trouble in the church\n"
   ]
  },
  {
   "type": "para",
   "marker": "p",
   "content": [
    {
     "type": "verse",
     "marker": "v",
     "number": "1",
     "sid": "3JN 1:1"
    },
    {
     "type": "note",
     "marker": "x",
     "content": [
      {
       "type": "char",
       "marker": "xo",
       "content": [
        "1: "
       ]
      },
      {
       "type": "char",
       "marker": "xt",
       "content": [
        "Acts 19:29; Rom 16:23; 1Cor 1:14."
       ]
      }
     ],
     "caller": "+"
    },
    "This letter is from Yohan the elder¦154477 to my dear friend Gaius¦154478 who I love ",
    {
     "type": "char",
     "marker": "add",
     "content": [
      "because we both"
     ]
    },
    " follow the truth¦154485.\n",
    {
     "type": "para",
     "marker": "rem",
     "content": [
      "/s1 Gaius Commended for His Hospitality\n"
     ]
    }
   ]
  },
  {
   "type": "para",
   "marker": "p",
   "content": [
    {
     "type": "verse",
     "marker": "v",
     "number": "2",
     "sid": "3JN 1:2"
    },
    "My dear friend, I trust that you are healthy¦154493 and doing well in everything just as you are also doing well spiritually.\n",
    {
     "type": "verse",
     "marker": "v",
     "number": "3",
     "sid": "3JN 1:3"
    },
    "I was very happy when some of our ",
    {
     "type": "char",
     "marker": "add",
     "content": [
      "spiritual"
     ]
    },
    " brothers¦154503 came and told us about your¦154507 faithfulness to the truth and how you are living it out.\n",
    {
     "type": "verse",
     "marker": "v",
     "number": "4",
     "sid": "3JN 1:4"
    },
    "Nothing makes me more happy than hearing¦154524 that other believers that I’ve helped are living out the truth¦154530.\n"
   ]
  },
  {
   "type": "para",
   "marker": "s1",
   "content": [
    "Praising Gaius\n"
   ]
  },
  {
   "type": "para",
   "marker": "rem",
   "content": [
    "/s1 Caring for the Lord’s Workers\n"
   ]
  },
  {
   "type": "para",
   "marker": "rem",
   "content": [
    "/s1 Gaius Is Praised\n"
   ]
  },
  {
   "type": "para",
   "marker": "p",
   "content": [
    {
     "type": "verse",
     "marker": "v",
     "number": "5",
     "sid": "3JN 1:5"
    },
    "My dear friend, you are faithful¦154533 in what you do for other believers¦154541. Even strangers¦154546\n",
    {
     "type": "verse",
     "marker": "v",
     "number": "6",
     "sid": "3JN 1:6"
    },
    "have told the assembly¦154553 about your¦154549 caring for them before¦154552 sending them on. Your¦154549 actions will be praised by ",
    {
     "type": "char",
     "marker": "nd",
     "content": [
      "God¦154563"
     ]
    },
    "\n",
    {
     "type": "verse",
     "marker": "v",
     "number": "7",
     "sid": "3JN 1:7"
    },
    "because¦154565 they¦154570 went¦154570 out to serve God, not getting any help from the unbelievers.\n",
    {
     "type": "verse",
     "marker": "v",
     "number": "8",
     "sid": "3JN 1:8"
    },
    "We should be supporting¦154580 believers like them so that we may also become¦154586 their workmates in sharing the truth¦154590.\n"
   ]
  },
  {
   "type": "para",
   "marker": "s1",
   "content": [
    "Diotrephes and Demetrius\n"
   ]
  },
  {
   "type": "para",
   "marker": "p",
   "content": [
    {
     "type": "verse",
     "marker": "v",
     "number": "9",
     "sid": "3JN 1:9"
    },
    "I wrote¦154591 something¦154593 to the assembly¦154595, but Diotrephes¦154600 won’t¦154601 listen to us—he always wants the limelight for himself.\n",
    {
     "type": "verse",
     "marker": "v",
     "number": "10",
     "sid": "3JN 1:10"
    },
    "Because¦154604 of that, if I do end up coming, I will be reminding¦154609 him about what he’s been doing¦154614—rambling¦154617 on against¦154617 us with evil¦154616 talks, and then, not being¦154622 happy with that, he doesn’t accept other believers¦154629 and expels them from the assembly¦154638 then forbids¦154634 others from accepting¦154627 them either.\n"
   ]
  },
  {
   "type": "para",
   "marker": "p",
   "content": [
    {
     "type": "verse",
     "marker": "v",
     "number": "11",
     "sid": "3JN 1:11"
    },
    "My dear friend, don’t¦154641 copy the evil things ",
    {
     "type": "char",
     "marker": "add",
     "content": [
      "that others do"
     ]
    },
    ", just the good things. Anyone who does what is good belongs to God—anyone who does evil things has not seen¦154658 God.\n"
   ]
  },
  {
   "type": "para",
   "marker": "p",
   "content": [
    {
     "type": "verse",
     "marker": "v",
     "number": "12",
     "sid": "3JN 1:12"
    },
    "Demetrius¦154661 has been talked about by everyone and even the truth¦154672 itself¦154667 speaks. We have also spoken about him, and you¦154679 know that what we¦154674 say is true.\n"
   ]
  },
  {
   "type": "para",
   "marker": "s1",
   "content": [
    "Closing\n"
   ]
  },
  {
   "type": "para",
   "marker": "rem",
   "content": [
    "/s1 Final Greetings\n"
   ]
  },
  {
   "type": "para",
   "marker": "rem",
   "content": [
    "/s1 Conclusion\n"
   ]
  },
  {
   "type": "para",
   "marker": "p",
   "content": [
    {
     "type": "verse",
     "marker": "v",
     "number": "13",
     "sid": "3JN 1:13"
    },
    "I had many things I wanted to write¦154692 about, but¦154694 won’t¦154695 do it by means of ink¦154699 and¦154700 pen¦154701,\n",
    {
     "type": "verse",
     "marker": "v",
     "number": "14",
     "sid": "3JN 1:14"
    },
    "but¦154707 instead I hope to see¦154711 you¦154710 soon and¦154712 then we¦154717 can speak¦154717 face to face.\n"
   ]
  },
  {
   "type": "para",
   "marker": "p",
   "content": [
    {
     "type": "verse",
     "marker": "v",
     "number": "15",
     "sid": "3JN 1:15"
    },
    "Wishing all peace and happiness for you. ",
    {
     "type": "char",
     "marker": "add",
     "content": [
      "Your"
     ]
    },
    " friends here also greet you. Please greet ",
    {
     "type": "char",
     "marker": "add",
     "content": [
      "our"
     ]
    },
    " friends there by name.\n"
   ]
  }
 ]
}