{
  "book": {
    "bookCode": "JOL",
    "description": "- Open English Translation—Readers' Version (OET-RV) v0.0.01",
    "meta": [
      {
        "usfm": "3.0"
      },
      {
        "ide": "UTF-8"
      },
      {
        "rem": "ESFM v0.6 JOL"
      },
      {
        "rem": "disabledWORDTABLE OET_OT_word_table.tsv"
      },
      {
        "h": "Yoel"
      },
      {
        "toc1": "Yoel"
      },
      {
        "toc2": "Yoel"
      },
      {
        "toc3": "Yoel"
      },
      {
        "mt1": "Yoel"
      },
      {
        "is1": "Introduction"
      },
      {
        "ip": "This document, it's written of me hep‑at hundred (400) year(s) and ke me five hundred (500) year(s) naa of not yet born the Messiah, of time iyan migmandu of other nations the kings of Pirsya. The migpangguhud of this story iyan prophet Huwil child of Pituwil."
      },
      {
        "ip": "Written this document due to because revelation of God ki Huwil the concerning the warning of judging and peglegpad of God of nations. Te pegkeyitabu here, saw rin the one palinneu of arrival of day of Master God, the time iyan peglegpad of God of that migsupak of igkeupii rin good. Impanengneng of prophet the pegpangumew of Master God of people so that eg-inniyug them of sins dan. Impanengneng din again the promise of Master God igpalibed din the good living of his people and egpanalanginan din them. Written again here of this document the promise of Master God egpeuyan he of Spirit din there to all his people."
      },
      {
        "iot": "Main components of this “book”"
      },
      {
        "io1": [
          "The salerep iyan the pegdalapak of me talangas",
          {
            "ior": "1:1–2:17",
            "closing": "\\ior*"
          }
        ]
      },
      {
        "io1": [
          "The promise of pegpalibed of good living",
          {
            "ior": "2:18-27",
            "closing": "\\ior*"
          }
        ]
      },
      {
        "io1": [
          "The day of Master God",
          {
            "ior": "2:28–3:21",
            "closing": "\\ior*"
          }
        ]
      },
      {
        "rem": [
          "This is still a very early look into the unfinished text of the",
          {
            "em": "Open English Translation",
            "closing": "\\em*"
          },
          "of the Bible. Please double-check the text in advance before using in public."
        ]
      },
      {
        "ie": ""
      }
    ]
  },
  "chapters": [
    {
      "chapterNumber": "1",
      "contents": [
        {
          "p": null
        },
        {
          "verseNumber": "1",
          "contents": [
            "◘",
            {
              "s1": "The peglungku due to me talangas"
            },
            {
              "rem": "/s1 Lament over the Ruin of the Country; An Invasion of Locusts; The People Mourn the Destruction of the Crops; The day of the Lord; Mourning over the Locust Plague"
            },
            {
              "q1": ""
            }
          ],
          "verseText": "◘"
        },
        {
          "verseNumber": "2",
          "contents": [
            "◘",
            {
              "q2": "…"
            },
            {
              "q1": "…"
            },
            {
              "q2": "…"
            },
            {
              "q1": ""
            }
          ],
          "verseText": "◘ … … …"
        },
        {
          "verseNumber": "3",
          "contents": [
            "◘",
            {
              "q2": "…"
            },
            {
              "q2": "…"
            },
            {
              "q1": ""
            }
          ],
          "verseText": "◘ … …"
        },
        {
          "verseNumber": "4",
          "contents": [
            "◘",
            {
              "q2": "…"
            },
            {
              "q2": "…"
            },
            {
              "q2": "…"
            },
            {
              "q1": ""
            }
          ],
          "verseText": "◘ … … …"
        },
        {
          "verseNumber": "5",
          "contents": [
            "◘",
            {
              "q2": "…"
            },
            {
              "b": ""
            },
            {
              "q1": ""
            }
          ],
          "verseText": "◘ …"
        },
        {
          "verseNumber": "6",
          "contents": [
            {
              "x": [
                "+",
                {
                  "xo": "1:6:"
                },
                {
                  "xt": "Rev 9:8."
                }
              ],
              "closing": "\\x*"
            },
            "◘",
            {
              "q2": "…"
            },
            {
              "q2": "…"
            },
            {
              "q1": ""
            }
          ],
          "verseText": "◘ … …"
        },
        {
          "verseNumber": "7",
          "contents": [
            "◘",
            {
              "q2": "…"
            },
            {
              "q2": "…"
            },
            {
              "b": ""
            },
            {
              "q1": ""
            }
          ],
          "verseText": "◘ … …"
        },
        {
          "verseNumber": "8",
          "contents": [
            "◘",
            {
              "q2": "…"
            },
            {
              "q1": ""
            }
          ],
          "verseText": "◘ …"
        },
        {
          "verseNumber": "9",
          "contents": [
            "◘",
            {
              "q2": "…"
            },
            {
              "q1": ""
            }
          ],
          "verseText": "◘ …"
        },
        {
          "verseNumber": "10",
          "contents": [
            "◘",
            {
              "q2": "…"
            },
            {
              "q2": "…"
            },
            {
              "q1": ""
            }
          ],
          "verseText": "◘ … …"
        },
        {
          "verseNumber": "11",
          "contents": [
            "◘",
            {
              "q2": "…"
            },
            {
              "q2": "…"
            },
            {
              "q1": ""
            }
          ],
          "verseText": "◘ … …"
        },
        {
          "verseNumber": "12",
          "contents": [
            "◘",
            {
              "q2": "…"
            },
            {
              "q1": "…"
            },
            {
              "q1": ""
            },
            {
              "rem": "/s1 A Call to Repentance and Prayer; A Call to Repentance"
            }
          ],
          "verseText": "◘ … …"
        },
        {
          "verseNumber": "13",
          "contents": [
            "◘",
            {
              "q2": "…"
            },
            {
              "q1": "…"
            },
            {
              "q2": "…"
            },
            {
              "q1": ""
            }
          ],
          "verseText": "◘ … … …"
        },
        {
          "verseNumber": "14",
          "contents": [
            "◘",
            {
              "q1": "…"
            },
            {
              "q2": "…"
            },
            {
              "q1": "…"
            },
            {
              "q1": ""
            }
          ],
          "verseText": "◘ … … …"
        },
        {
          "verseNumber": "15",
          "contents": [
            {
              "x": [
                "+",
                {
                  "xo": "1:15:"
                },
                {
                  "xt": "Isa 13:6."
                }
              ],
              "closing": "\\x*"
            },
            "◘",
            {
              "q2": "…"
            },
            {
              "q1": "…"
            },
            {
              "b": ""
            },
            {
              "q1": ""
            }
          ],
          "verseText": "◘ … …"
        },
        {
          "verseNumber": "16",
          "contents": [
            "◘",
            {
              "q1": "…"
            },
            {
              "q1": ""
            }
          ],
          "verseText": "◘ …"
        },
        {
          "verseNumber": "17",
          "contents": [
            "◘",
            {
              "q1": "…"
            },
            {
              "q1": "…"
            },
            {
              "q1": ""
            }
          ],
          "verseText": "◘ … …"
        },
        {
          "verseNumber": "18",
          "contents": [
            "◘",
            {
              "q1": "…"
            },
            {
              "q2": "…"
            },
            {
              "q1": "…"
            },
            {
              "q1": ""
            }
          ],
          "verseText": "◘ … … …"
        },
        {
          "verseNumber": "19",
          "contents": [
            "◘",
            {
              "q2": "…"
            },
            {
              "q2": "…"
            },
            {
              "q1": ""
            }
          ],
          "verseText": "◘ … …"
        },
        {
          "verseNumber": "20",
          "contents": [
            "◘",
            {
              "q2": "…"
            },
            {
              "q2": "…"
            }
          ],
          "verseText": "◘ … …"
        }
      ]
    },
    {
      "chapterNumber": "2",
      "contents": [
        {
          "s1": "The day of Master God"
        },
        {
          "rem": "/s1 An Army of Locusts; Locusts Invade like an Army; The Locusts as a Warning of the Day of the Lord"
        },
        {
          "q1": null
        },
        {
          "verseNumber": "1",
          "contents": [
            "◘",
            {
              "q2": "…"
            },
            {
              "q1": "…"
            },
            {
              "q2": "…"
            },
            {
              "q1": ""
            }
          ],
          "verseText": "◘ … … …"
        },
        {
          "verseNumber": "2",
          "contents": [
            "◘",
            {
              "q2": "…"
            },
            {
              "q1": "…"
            },
            {
              "q2": "…"
            },
            {
              "q1": "…"
            },
            {
              "q2": "…"
            },
            {
              "b": ""
            },
            {
              "q1": ""
            }
          ],
          "verseText": "◘ … … … … …"
        },
        {
          "verseNumber": "3",
          "contents": [
            "◘",
            {
              "q1": "…"
            },
            {
              "q2": "…"
            },
            {
              "q1": "…"
            },
            {
              "q1": ""
            }
          ],
          "verseText": "◘ … … …"
        },
        {
          "verseNumber": "4",
          "contents": [
            {
              "x": [
                "+",
                {
                  "xo": "2:4-5:"
                },
                {
                  "xt": "Rev 9:7-9."
                }
              ],
              "closing": "\\x*"
            },
            "◘",
            {
              "q2": "…"
            },
            {
              "q1": ""
            }
          ],
          "verseText": "◘ …"
        },
        {
          "verseNumber": "5",
          "contents": [
            "◘",
            {
              "q2": "…"
            },
            {
              "q2": "…"
            },
            {
              "q1": "…"
            },
            {
              "q1": ""
            }
          ],
          "verseText": "◘ … … …"
        },
        {
          "verseNumber": "6",
          "contents": [
            "◘",
            {
              "q2": "…"
            },
            {
              "q1": ""
            }
          ],
          "verseText": "◘ …"
        },
        {
          "verseNumber": "7",
          "contents": [
            "◘",
            {
              "q2": "…"
            },
            {
              "q1": "…"
            },
            {
              "q2": "…"
            },
            {
              "q1": ""
            }
          ],
          "verseText": "◘ … … …"
        },
        {
          "verseNumber": "8",
          "contents": [
            "◘",
            {
              "q2": "…"
            },
            {
              "q1": "…"
            },
            {
              "q2": "…"
            },
            {
              "q1": ""
            }
          ],
          "verseText": "◘ … … …"
        },
        {
          "verseNumber": "9",
          "contents": [
            "◘",
            {
              "q2": "…"
            },
            {
              "q2": "…"
            },
            {
              "q2": "…"
            },
            {
              "b": ""
            },
            {
              "q1": ""
            }
          ],
          "verseText": "◘ … … …"
        },
        {
          "verseNumber": "10",
          "contents": [
            {
              "x": [
                "+",
                {
                  "xo": "2:10:"
                },
                {
                  "xt": "Rev 8:12."
                }
              ],
              "closing": "\\x*"
            },
            "◘",
            {
              "q2": "…"
            },
            {
              "q1": "…"
            },
            {
              "q2": "…"
            },
            {
              "q1": ""
            }
          ],
          "verseText": "◘ … … …"
        },
        {
          "verseNumber": "11",
          "contents": [
            {
              "x": [
                "+",
                {
                  "xo": "2:11:"
                },
                {
                  "xt": "Rev 6:17."
                }
              ],
              "closing": "\\x*"
            },
            "◘",
            {
              "q2": "…"
            },
            {
              "q1": "…"
            },
            {
              "q2": "…"
            },
            {
              "q1": "…"
            },
            {
              "q2": "…"
            },
            {
              "s1": "The pegbanasal of God eg-inniyug of sin"
            },
            {
              "rem": "/s1 Rend Your Heart; A Call to Repentance"
            },
            {
              "q1": ""
            }
          ],
          "verseText": "◘ … … … … …"
        },
        {
          "verseNumber": "12",
          "contents": [
            "◘",
            {
              "q2": "…"
            },
            {
              "q2": "…"
            },
            {
              "q1": ""
            }
          ],
          "verseText": "◘ … …"
        },
        {
          "verseNumber": "13",
          "contents": [
            "◘",
            {
              "q2": "…"
            },
            {
              "b": ""
            },
            {
              "q1": "…"
            },
            {
              "q2": "…"
            },
            {
              "q2": "…"
            },
            {
              "q1": ""
            }
          ],
          "verseText": "◘ … … … …"
        },
        {
          "verseNumber": "14",
          "contents": [
            "◘",
            {
              "q2": "…"
            },
            {
              "q2": "…"
            },
            {
              "q1": ""
            }
          ],
          "verseText": "◘ … …"
        },
        {
          "verseNumber": "15",
          "contents": [
            "◘",
            {
              "q2": "…"
            },
            {
              "q2": "…"
            },
            {
              "q1": ""
            }
          ],
          "verseText": "◘ … …"
        },
        {
          "verseNumber": "16",
          "contents": [
            "◘",
            {
              "q1": "…"
            },
            {
              "q1": "…"
            },
            {
              "q2": "…"
            },
            {
              "q1": ""
            }
          ],
          "verseText": "◘ … … …"
        },
        {
          "verseNumber": "17",
          "contents": [
            "◘",
            {
              "q2": "…"
            },
            {
              "q1": "…"
            },
            {
              "q2": "…"
            },
            {
              "q1": "…"
            },
            {
              "q2": "…"
            },
            {
              "s1": "The pegpalibed of kalambeg of land"
            },
            {
              "rem": "/s1 God Restores Fertility to the Land; The Lord's Promise of Restoration; God's Response and Promise; Israel forgiven and restored; The Lord's Answer"
            },
            {
              "q1": ""
            }
          ],
          "verseText": "◘ … … … … …"
        },
        {
          "verseNumber": "18",
          "contents": [
            "◘",
            {
              "q2": "…"
            },
            {
              "q1": ""
            }
          ],
          "verseText": "◘ …"
        },
        {
          "verseNumber": "19",
          "contents": [
            "◘",
            {
              "q1": "…"
            },
            {
              "q2": "…"
            },
            {
              "q1": "…"
            },
            {
              "q1": ""
            }
          ],
          "verseText": "◘ … … …"
        },
        {
          "verseNumber": "20",
          "contents": [
            "◘",
            {
              "q1": "…"
            },
            {
              "q2": "…"
            },
            {
              "q2": "…"
            },
            {
              "q1": "…"
            },
            {
              "q1": "…"
            },
            {
              "b": ""
            },
            {
              "q1": ""
            }
          ],
          "verseText": "◘ … … … … …"
        },
        {
          "verseNumber": "21",
          "contents": [
            "◘",
            {
              "q1": "…"
            },
            {
              "q1": ""
            }
          ],
          "verseText": "◘ …"
        },
        {
          "verseNumber": "22",
          "contents": [
            "◘",
            {
              "q2": "…"
            },
            {
              "q1": "…"
            },
            {
              "b": ""
            },
            {
              "q1": ""
            }
          ],
          "verseText": "◘ … …"
        },
        {
          "verseNumber": "23",
          "contents": [
            "◘",
            {
              "q2": "…"
            },
            {
              "q1": "…"
            },
            {
              "q2": "…"
            },
            {
              "q1": ""
            }
          ],
          "verseText": "◘ … … …"
        },
        {
          "verseNumber": "24",
          "contents": [
            "◘",
            {
              "q2": "…"
            },
            {
              "q1": ""
            }
          ],
          "verseText": "◘ …"
        },
        {
          "verseNumber": "25",
          "contents": [
            "◘",
            {
              "q2": "…"
            },
            {
              "q2": "…"
            },
            {
              "q1": ""
            }
          ],
          "verseText": "◘ … …"
        },
        {
          "verseNumber": "26",
          "contents": [
            "◘",
            {
              "q1": "…"
            },
            {
              "q2": "…"
            },
            {
              "q1": "…"
            },
            {
              "q1": ""
            }
          ],
          "verseText": "◘ … … …"
        },
        {
          "verseNumber": "27",
          "contents": [
            "◘",
            {
              "q2": "…"
            },
            {
              "q1": "…"
            },
            {
              "s1": "The pegbehey of God of Spirit din"
            },
            {
              "rem": "/s1 The Lord's Promise of His Spirit; The Day of the Lord; God's Spirit Poured Out"
            },
            {
              "q1": ""
            }
          ],
          "verseText": "◘ … …"
        },
        {
          "verseNumber": "28",
          "contents": [
            "◘",
            {
              "q1": "…"
            },
            {
              "q2": "…"
            },
            {
              "q1": "…"
            },
            {
              "q2": "…"
            },
            {
              "q1": ""
            }
          ],
          "verseText": "◘ … … … …"
        },
        {
          "verseNumber": "29",
          "contents": [
            "◘",
            {
              "q2": "…"
            },
            {
              "s1": "The warning concerning the day of Master"
            },
            {
              "q1": ""
            }
          ],
          "verseText": "◘ …"
        },
        {
          "verseNumber": "30",
          "contents": [
            "◘",
            {
              "q2": "…"
            },
            {
              "q1": ""
            }
          ],
          "verseText": "◘ …"
        },
        {
          "verseNumber": "31",
          "contents": [
            {
              "x": [
                "+",
                {
                  "xo": "2:31:"
                },
                {
                  "xt": "Mat 24:29; Mrk 13:24-25; Luk 21:25; Rev 6:12-13."
                }
              ],
              "closing": "\\x*"
            },
            "◘",
            {
              "q2": "…"
            },
            {
              "q1": ""
            }
          ],
          "verseText": "◘ …"
        },
        {
          "verseNumber": "32",
          "contents": [
            {
              "x": [
                "+",
                {
                  "xo": "2:28-32:"
                },
                {
                  "xt": "Acts 2:17-21."
                }
              ],
              "closing": "\\x*"
            },
            "◘",
            {
              "q1": "…"
            },
            {
              "q2": "…"
            },
            {
              "q1": "…"
            }
          ],
          "verseText": "◘ … … …"
        }
      ]
    },
    {
      "chapterNumber": "3",
      "contents": [
        {
          "s1": "The judging of God of nations"
        },
        {
          "rem": "/s1 God Will Judge the Nations; Judgment against Enemy Nations; The Nations Judged"
        },
        {
          "q1": null
        },
        {
          "verseNumber": "1",
          "contents": [
            "◘",
            {
              "q1": "…"
            },
            {
              "q2": "…"
            },
            {
              "q1": ""
            }
          ],
          "verseText": "◘ … …"
        },
        {
          "verseNumber": "2",
          "contents": [
            "◘",
            {
              "q2": "…"
            },
            {
              "q1": "…"
            },
            {
              "q2": "…"
            },
            {
              "q1": "…"
            },
            {
              "q2": "…"
            },
            {
              "q1": ""
            }
          ],
          "verseText": "◘ … … … … …"
        },
        {
          "verseNumber": "3",
          "contents": [
            "◘",
            {
              "q2": "…"
            },
            {
              "q2": "…"
            },
            {
              "p": ""
            }
          ],
          "verseText": "◘ … …"
        },
        {
          "verseNumber": "4",
          "contents": [
            {
              "x": [
                "+",
                {
                  "xo": "3:4-8:"
                },
                {
                  "xt": "Isa 23:1-18; Eze 26:1–28:26; Amos 1:9-10; Zech 9:1-4; Mat 11:21-22; Luk 10:13-14."
                }
              ],
              "closing": "\\x*"
            },
            "◘"
          ],
          "verseText": "◘"
        },
        {
          "verseNumber": "5",
          "contents": [
            "◘"
          ],
          "verseText": "◘"
        },
        {
          "verseNumber": "6",
          "contents": [
            "◘"
          ],
          "verseText": "◘"
        },
        {
          "verseNumber": "7",
          "contents": [
            "◘"
          ],
          "verseText": "◘"
        },
        {
          "verseNumber": "8",
          "contents": [
            "◘",
            {
              "q1": ""
            },
            {
              "rem": "/s1 Judgment in the Valley of Jehoshaphat"
            }
          ],
          "verseText": "◘"
        },
        {
          "verseNumber": "9",
          "contents": [
            "◘",
            {
              "q2": "…"
            },
            {
              "q2": "…"
            },
            {
              "q2": "…"
            },
            {
              "q1": ""
            }
          ],
          "verseText": "◘ … … …"
        },
        {
          "verseNumber": "10",
          "contents": [
            {
              "x": [
                "+",
                {
                  "xo": "3:10:"
                },
                {
                  "xt": "Isa 2:4; Mic 4:3."
                }
              ],
              "closing": "\\x*"
            },
            "◘",
            {
              "q2": "…"
            },
            {
              "q1": "…"
            },
            {
              "q1": ""
            }
          ],
          "verseText": "◘ … …"
        },
        {
          "verseNumber": "11",
          "contents": [
            "◘",
            {
              "q2": "…"
            },
            {
              "b": ""
            },
            {
              "q1": "…"
            },
            {
              "b": ""
            },
            {
              "q1": ""
            }
          ],
          "verseText": "◘ … …"
        },
        {
          "verseNumber": "12",
          "contents": [
            "◘",
            {
              "q2": "…"
            },
            {
              "q2": "…"
            },
            {
              "q1": ""
            }
          ],
          "verseText": "◘ … …"
        },
        {
          "verseNumber": "13",
          "contents": [
            "◘",
            {
              "q2": "…"
            },
            {
              "q2": "…"
            },
            {
              "q1": ""
            }
          ],
          "verseText": "◘ … …"
        },
        {
          "verseNumber": "14",
          "contents": [
            "◘",
            {
              "q2": "…"
            },
            {
              "q1": ""
            }
          ],
          "verseText": "◘ …"
        },
        {
          "verseNumber": "15",
          "contents": [
            "◘",
            {
              "q2": "…"
            },
            {
              "q1": ""
            },
            {
              "rem": "/s1 God Will Bless His People"
            }
          ],
          "verseText": "◘ …"
        },
        {
          "verseNumber": "16",
          "contents": [
            {
              "x": [
                "+",
                {
                  "xo": "3:16:"
                },
                {
                  "xt": "Amos 1:2."
                }
              ],
              "closing": "\\x*"
            },
            "◘",
            {
              "q2": "…"
            },
            {
              "q2": "…"
            },
            {
              "s1": "The blessing of God of his people"
            },
            {
              "rem": "/s1 The Glorious Future of Judah; Blessings for God's People"
            },
            {
              "q1": "…"
            },
            {
              "q1": ""
            }
          ],
          "verseText": "◘ … … …"
        },
        {
          "verseNumber": "17",
          "contents": [
            "◘",
            {
              "q1": "…"
            },
            {
              "q1": "…"
            },
            {
              "q2": "…"
            },
            {
              "q1": ""
            }
          ],
          "verseText": "◘ … … …"
        },
        {
          "verseNumber": "18",
          "contents": [
            "◘",
            {
              "q2": "…"
            },
            {
              "q1": "…"
            },
            {
              "q1": "…"
            },
            {
              "q2": "…"
            },
            {
              "q2": "…"
            },
            {
              "b": ""
            },
            {
              "q1": ""
            }
          ],
          "verseText": "◘ … … … … …"
        },
        {
          "verseNumber": "19",
          "contents": [
            "◘",
            {
              "q2": "…"
            },
            {
              "q2": "…"
            },
            {
              "q1": ""
            }
          ],
          "verseText": "◘ … …"
        },
        {
          "verseNumber": "20",
          "contents": [
            "◘",
            {
              "q1": ""
            }
          ],
          "verseText": "◘"
        },
        {
          "verseNumber": "21",
          "contents": [
            "◘",
            {
              "q2": "…"
            },
            {
              "q1": "…"
            }
          ],
          "verseText": "◘ … …"
        }
      ]
    }
  ],
  "_messages": {
    "_warnings": []
  }
}
